[{"address": "0x3ff33d9162ad47660083d7dc4bc02fb231c81677", "address_type": "Smart Contract", "annotation": "", "balance": 5304.2237070823985}, {"address": "0x088ee5007c98a9677165d78dd2109ae4a3d04d0c", "address_type": "DEX", "annotation": "YFI, SushiSwap", "balance": 2670.788422130576}, {"address": "0xb1cff81b9305166ff1efc49a129ad2afcd7bcf19", "address_type": "Smart Contract", "annotation": "", "balance": 1942.3030286599376}, {"address": "0x5165d24277cd063f5ac44efd447b27025e888f37", "address_type": "Token", "annotation": "Aave interest bearing YFI (aYFI), Aave, DeFi, Aave V2", "balance": 1722.258055066307}, {"address": "0x3dfd23a6c5e8bbcfc9581d2e864a68feb6a076d3", "address_type": "Smart Contract", "annotation": "Lending Pool Core V1, Lending Pool Core, Aave, Loans", "balance": 1656.9755745326433}, {"address": "0xe14d13d8b3b85af791b2aadd661cdbd5e6097db1", "address_type": "Token", "annotation": "", "balance": 1390.4298289660974}, {"address": "0x2faf487a4414fe77e2327f0bf4ae2a264a776ad2", "address_type": "Wallet", "annotation": "FTX Exchange, FTX", "balance": 1013.3817274947139}, {"address": "0x47ac0fb4f2d84898e4d9e7b4dab3c24507a6d503", "address_type": "Wallet", "annotation": "", "balance": 900.0}, {"address": "0xba37b002abafdd8e89a1995da52740bbc013d992", "address_type": "Token", "annotation": "Governance Staking, ygov.finance", "balance": 899.8926705744213}, {"address": "0x3f5ce5fbfe3e9af3971dd833d26ba9b5c936f0be", "address_type": "Wallet", "annotation": "Exchange, Binance, Binance_1, Exchange Wallet, Binance 1", "balance": 857.5089419847991}, {"address": "0x675938d86a6a4651b6dbba7529117fb0b557ccf2", "address_type": "Wallet", "annotation": "", "balance": 525.4877877881756}, {"address": "0xbe0eb53f46cd790cd13851d5eff43d12404d33e8", "address_type": "Wallet", "annotation": "Binance 7, Binance, Cold Wallet, Exchange", "balance": 500.0}, {"address": "0x1149e9143c407f3be1df24c463e48963c6de1715", "address_type": "Wallet", "annotation": "", "balance": 363.2699999999995}, {"address": "0x5f65f7b609678448494de4c87521cdf6cef1e932", "address_type": "Smart Contract", "annotation": "", "balance": 361.15165154118364}, {"address": "0x34a4c5d747f54d5e3a3f66eb6ef3f697f474fd90", "address_type": "Wallet", "annotation": "", "balance": 340.0}, {"address": "0x555981b82743aa443cb1c3002c85ba9d795d4596", "address_type": "Smart Contract", "annotation": "", "balance": 324.3416034902954}, {"address": "0xf977814e90da44bfa03b6295a0616a897441acec", "address_type": "Wallet", "annotation": "Binance 8, Binance, Exchange", "balance": 300.0}, {"address": "0xf7e1974393108d506ac8ce06da4cb002a516093f", "address_type": "Wallet", "annotation": "", "balance": 286.9106263380467}, {"address": "0x3f7af19e7e465c9aa5075a90b831f08306a15a16", "address_type": "Wallet", "annotation": "", "balance": 276.7117}, {"address": "0x5f776c9500ec542946d6e20447a5cfce2a79b883", "address_type": "Wallet", "annotation": "", "balance": 237.602118753276}, {"address": "0x4deb3edd991cfd2fcdaa6dcfe5f1743f6e7d16a6", "address_type": "Wallet", "annotation": "", "balance": 229.9925867235031}, {"address": "0x742d35cc6634c0532925a3b844bc454e4438f44e", "address_type": "Wallet", "annotation": "Bitfinex_5, Exchange Wallet, Exchange, Fiat Gateway, Bitfinex 2, Bitfinex 5, Bitfinex", "balance": 223.11062}, {"address": "0x102af6aa34c17b9377447ab91e73acbeb76b8501", "address_type": "Smart Contract", "annotation": "", "balance": 216.5}, {"address": "0x3eb2e01e4a6d1be679ab5bd73c3d6ddb568e9cde", "address_type": "Smart Contract", "annotation": "", "balance": 215.9179382293252}, {"address": "0xf4efdc3416bdcf258c157e95b8b3ef800c5c93f9", "address_type": "Smart Contract", "annotation": "", "balance": 212.61975}, {"address": "0x68c97d275f2e73e7059ffc191c16f660b88f6370", "address_type": "Smart Contract", "annotation": "", "balance": 211.50551195459158}, {"address": "0x1494ca1f11d487c2bbe4543e90080aeba4ba3c2b", "address_type": "Token", "annotation": "", "balance": 206.03490956782824}, {"address": "0xa8823dc09d486718e8e2eeb9b82de4d5d755f1ef", "address_type": "Smart Contract", "annotation": "", "balance": 203.7586787058177}, {"address": "0xb1a1ae5c34ceec969e1f7e176fe8a0506ce044d6", "address_type": "Smart Contract", "annotation": "", "balance": 202.1446059001353}, {"address": "0x42ad05d4f56456230c023cd023ddbc9935903ab4", "address_type": "Wallet", "annotation": "", "balance": 192.40174619681252}, {"address": "0xde2af899040536884e062d3a334f2dd36f34b4a4", "address_type": "Token", "annotation": "", "balance": 178.76923769238414}, {"address": "0xaea97b739dcd6f5b586586cb7a538d60ba96a757", "address_type": "Multisig", "annotation": "", "balance": 170.35958202000003}, {"address": "0x43adde52c6c142912662d3e427709db5cac9b811", "address_type": "Wallet", "annotation": "", "balance": 161.94546656999998}, {"address": "0x764e7b7bfeb3bb11f43d17621b8197aeee4e781b", "address_type": "Wallet", "annotation": "", "balance": 160.47313929148714}, {"address": "0xbcd5000f5c522856e710c5d274bb672b2f2eefbf", "address_type": "Wallet", "annotation": "", "balance": 151.99299999999997}, {"address": "0x6cc5f688a315f3dc28a7781717a9a798a59fda7b", "address_type": "Wallet", "annotation": "Okex, Exchange, OKEx 1, OKEx, Okex 1, Derivatives, Exchange Wallet", "balance": 148.34317099167697}, {"address": "0x0548f59fee79f8832c299e01dca5c76f034f558e", "address_type": "Wallet", "annotation": "", "balance": 147.91939714440548}, {"address": "0x26d3ff4dc8439709c397304625a30365bd7301dc", "address_type": "Wallet", "annotation": "", "balance": 140.375718}, {"address": "0x3744da57184575064838bbc87a0fc791f5e39ea2", "address_type": "Wallet", "annotation": "", "balance": 137.880736}, {"address": "0x438cdc28a5e9166dacf475348b56d02ecd05174a", "address_type": "Wallet", "annotation": "", "balance": 124.1707}, {"address": "0x955886d5d84ba3b9a9eb307fe1becb39608b17e3", "address_type": "Wallet", "annotation": "", "balance": 122.22219999999997}, {"address": "0xae93b51dc5d59b22e09df78f9c9b1f3fe9ea93cf", "address_type": "Wallet", "annotation": "", "balance": 119.9996}, {"address": "0xc564ee9f21ed8a2d8e7e76c085740d5e4c5fafbe", "address_type": "Wallet", "annotation": "Fantom Bridge, Bridge", "balance": 115.64919637465071}, {"address": "0x63c61febe1647ed9a66f0b1f801f90dcaf5c7ac3", "address_type": "Smart Contract", "annotation": "", "balance": 109.14165482834433}, {"address": "0xd1002d0f89dfccc662b9b63e3eb0ab2d4c858ed8", "address_type": "Smart Contract", "annotation": "", "balance": 108.03181506849315}, {"address": "0x42a28addc15e627d19e780c89043b4b1d3629d34", "address_type": "Smart Contract", "annotation": "", "balance": 106.14939011500084}, {"address": "0xfb626333099a91ab677bcd5e9c71bc4dbe0238a8", "address_type": "Wallet", "annotation": "", "balance": 105.69589999999988}, {"address": "0xd0660cd418a64a1d44e9214ad8e459324d8157f1", "address_type": "Token", "annotation": "", "balance": 103.99848052666567}, {"address": "0xd520e3662f2af962dd6b42ad5b26d6ffca561296", "address_type": "Wallet", "annotation": "", "balance": 100.0}, {"address": "0x804fe81772f74da81dfa0be97b3b7feff323e2d6", "address_type": "Wallet", "annotation": "", "balance": 99.999544}, {"address": "0x404de972e8138c4982ace8bdd7fc0e755de33afd", "address_type": "Wallet", "annotation": "", "balance": 97.80291763000001}, {"address": "0x86904e32b0d7a8e1ab4dc4a02bae7ff93e9a2d33", "address_type": "Wallet", "annotation": "", "balance": 97.5499103100002}, {"address": "0x64e2c8b9083bd3e08075c49e8fad27786e1f1b87", "address_type": "Wallet", "annotation": "", "balance": 95.16547014936805}, {"address": "0x708396f17127c42383e3b9014072679b2f60b82f", "address_type": "Wallet", "annotation": "Binance 11, Binance", "balance": 94.571006679998}, {"address": "0x85b931a32a0725be14285b66f1a22178c672d69b", "address_type": "Wallet", "annotation": "Binance 10, Binance", "balance": 94.56495930999938}, {"address": "0xe93381fb4c4f14bda253907b18fad305d799241a", "address_type": "Wallet", "annotation": "Huobi, Huobi_10, Exchange Wallet, Huobi 10, Exchange", "balance": 93.7152485019762}, {"address": "0x0681d8db095565fe8a346fa0277bffde9c0edbbf", "address_type": "Wallet", "annotation": "Exchange, Binance, Binance_4, Exchange Wallet, Binance 4", "balance": 92.43927808000079}, {"address": "0x1671a3e4a2519a653e66e827ef6eae690ee86729", "address_type": "Wallet", "annotation": "", "balance": 89.2877067299995}, {"address": "0xa929022c9107643515f5c777ce9a910f0d1e490c", "address_type": "Smart Contract", "annotation": "", "balance": 87.00049999999999}, {"address": "0x924cd9b60f4173dcdd5254ddd38c4f9cab68fe6b", "address_type": "Wallet", "annotation": "", "balance": 86.3612000000006}, {"address": "0x2fdbadf3c4d5a8666bc06645b8358ab803996e28", "address_type": "DEX", "annotation": "", "balance": 83.59805846978718}, {"address": "0x564286362092d8e7936f0549571a803b203aaced", "address_type": "Wallet", "annotation": "Exchange, Binance, Binance_3, Exchange Wallet, Binance 3", "balance": 82.10842380000035}, {"address": "0x22acb809d08ae7c79f0b84513efce0577acfe514", "address_type": "Wallet", "annotation": "", "balance": 76.72384429400662}, {"address": "0xd628f7c481c7dd87f674870bec5d7a311fb1d9a2", "address_type": "Wallet", "annotation": "", "balance": 76.55730589999995}, {"address": "0x39eea0258a5c3e3c5092b2f910371d124592a7fb", "address_type": "Wallet", "annotation": "", "balance": 75.0000597407008}, {"address": "0x084632d878bbcba7513c5b07d5a77359cae9fcda", "address_type": "Wallet", "annotation": "", "balance": 71.72765658451169}, {"address": "0x029658352b1c5c6facf0dc8d57ac02b71811873d", "address_type": "Wallet", "annotation": "", "balance": 71.72765658451169}, {"address": "0x72ea797a3dd7b5249d0966f97acda3d7cd1436e0", "address_type": "Wallet", "annotation": "", "balance": 71.72765658451169}, {"address": "0x33060d5e944c8ce66f05fe6ee0c2e66d3f3660cf", "address_type": "Wallet", "annotation": "", "balance": 71.72765658451169}, {"address": "0x380a0ea94988e2b0b4f35f1ed54a18cb2197a32e", "address_type": "Wallet", "annotation": "", "balance": 71.72765658451169}, {"address": "0xe503b25b545409d24a71c7b03706be7f546e23f0", "address_type": "Wallet", "annotation": "", "balance": 71.72765658451169}, {"address": "0xc2e47b1a184e0149dcba6da95eda43280757cb5f", "address_type": "Wallet", "annotation": "", "balance": 71.72765658451169}, {"address": "0xcbad902cc3ca232410704656406dfd312305958a", "address_type": "Wallet", "annotation": "", "balance": 71.72765658451169}, {"address": "0xd3ebcb0445236d36734052a7cf68b6655be80f52", "address_type": "Wallet", "annotation": "", "balance": 71.72765658451169}, {"address": "0x07f5c3cf8a00186955b901f8748a63df65a0fea0", "address_type": "Wallet", "annotation": "", "balance": 71.72765658451169}, {"address": "0x60c7e122ff77a8e4487e79ef238c09dcb00f51ce", "address_type": "Wallet", "annotation": "", "balance": 71.72765658451169}, {"address": "0x13c66193f6c482ead13af027262d83c10f492505", "address_type": "Wallet", "annotation": "", "balance": 71.72765658451169}, {"address": "0x10ba7cc3f7f97cf538708b335f30a737c35b24a1", "address_type": "Wallet", "annotation": "", "balance": 69.28886694736822}, {"address": "0x80bf5c35d0918b08ceac49af3c983e9a6daa50c7", "address_type": "Wallet", "annotation": "", "balance": 67.258301}, {"address": "0xddfabcdc4d8ffc6d5beaf154f18b778f892a0740", "address_type": "Wallet", "annotation": "", "balance": 66.98919879056136}, {"address": "0x967159c42568a54d11a4761fc86a6089ed42b7ba", "address_type": "Wallet", "annotation": "", "balance": 65.79365}, {"address": "0x345d8e3a1f62ee6b1d483890976fd66168e390f2", "address_type": "Wallet", "annotation": "", "balance": 60.490241999999334}, {"address": "0x7dcf418d8bafbaf3ab7fcd5732d4a1d55c7bace7", "address_type": "Wallet", "annotation": "", "balance": 60.00000000000001}, {"address": "0xac5b5fa383b2807f90d9aaabd2ba6a3de790930f", "address_type": "Wallet", "annotation": "", "balance": 60.00000000000001}, {"address": "0xa1a7f9b59a5055e2e19d4a46ea47ebe45f4a4a23", "address_type": "Wallet", "annotation": "", "balance": 60.00000000000001}, {"address": "0x9af1e87395788a52b562633461cbccc4574cf795", "address_type": "Wallet", "annotation": "", "balance": 60.0}, {"address": "0x9bafa78fcbed7aa93247d0bdacb73c4249f0fe33", "address_type": "Wallet", "annotation": "", "balance": 60.0}, {"address": "0x99028a948194914e8602149481f5b84da1796798", "address_type": "Wallet", "annotation": "", "balance": 60.0}, {"address": "0xaf572a0c29117cfc537acf038e26fe8565b12566", "address_type": "Wallet", "annotation": "", "balance": 60.0}, {"address": "0xab0dc1ce7a33a664d44e9c7ef3c7cb57aa1e28b5", "address_type": "Wallet", "annotation": "", "balance": 60.0}, {"address": "0x2f17ea8c4064a7e259745116a28dfeef3099bd93", "address_type": "Wallet", "annotation": "", "balance": 60.0}, {"address": "0x1c1818b9ae1bdbaa747ad1c6f6b7f4a40534b0ef", "address_type": "Wallet", "annotation": "", "balance": 60.0}, {"address": "0x2ca42fcf0fad476232c0720a6891bb268b3abd57", "address_type": "Wallet", "annotation": "", "balance": 60.0}, {"address": "0x570a593e00f52c1c977fca4fe77fd1234752366c", "address_type": "Wallet", "annotation": "", "balance": 60.0}, {"address": "0xc1ab698ae9591e1d3e652b1c9d4618d305d929c8", "address_type": "Wallet", "annotation": "", "balance": 60.0}, {"address": "0xd16cab8cdda64bca9e60a3fad27063fde9861883", "address_type": "Wallet", "annotation": "", "balance": 60.0}, {"address": "0x70d7fc55c8a36c1470c8521424e76e6cd1b5eb8a", "address_type": "Wallet", "annotation": "", "balance": 60.0}, {"address": "0x6eb402118ec9d48bf03d3ce2f07beac24ca6b4e0", "address_type": "Wallet", "annotation": "", "balance": 60.0}, {"address": "0x0e0c6a23551ba6be04cca60d96ea70c595cc0483", "address_type": "Wallet", "annotation": "", "balance": 60.0}, {"address": "0x4e85c4a18e2dba38d45c5a4c0d4da2ab8dbe0e76", "address_type": "Wallet", "annotation": "", "balance": 59.99999999999999}]